[{"domain": ".riverisland.com", "expiry": 1725482248, "httpOnly": false, "name": "_dc_gtm_UA-101889523-1", "path": "/", "sameSite": "Lax", "secure": false, "value": "1"}, {"domain": ".riverisland.com", "expiry": 1760042188, "httpOnly": false, "name": "_ga_V9GPQLLNWP", "path": "/", "sameSite": "Lax", "secure": false, "value": "GS1.1.1725482187.1.0.1725482188.60.0.0"}, {"domain": ".riverisland.com", "expiry": 1725482248, "httpOnly": false, "name": "_gat_UA-101889523-1", "path": "/", "sameSite": "Lax", "secure": false, "value": "1"}, {"domain": ".riverisland.com", "expiry": 1733258189, "httpOnly": false, "name": "_gcl_au", "path": "/", "sameSite": "Lax", "secure": false, "value": "1.1.1852556160.1725482189"}, {"domain": ".riverisland.com", "expiry": 1725568588, "httpOnly": false, "name": "_gid", "path": "/", "sameSite": "Lax", "secure": false, "value": "GA1.2.1022779989.1725482189"}, {"domain": ".riverisland.com", "expiry": 1757018188, "httpOnly": false, "name": "cookie_consent", "path": "/", "sameSite": "Lax", "secure": false, "value": "{\"analytics\":true,\"marketing\":true,\"version\":1.02,\"entry\":false,\"dateSet\":\"2024-09-04T20:36:28.840Z\"}"}, {"domain": ".riverisland.com", "expiry": 1725483986, "httpOnly": false, "name": "_cs_mk_ga", "path": "/", "sameSite": "None", "secure": true, "value": "0.6074841525244714_1725482186753"}, {"domain": "www.riverisland.com", "expiry": 1741034184, "httpOnly": true, "name": "tcpl_user", "path": "/", "sameSite": "Lax", "secure": true, "value": "%7b35904195-0ded-409f-bb62-d98bba406b73%7d"}, {"domain": "www.riverisland.com", "expiry": 1725485785, "httpOnly": false, "name": "tdt", "path": "/", "sameSite": "Lax", "secure": false, "value": "D"}, {"domain": "www.riverisland.com", "httpOnly": false, "name": "tcpl_sessId", "path": "/", "sameSite": "Lax", "secure": true, "value": "71d5994ed51a47c48d3e6e9bdd5a91f0"}, {"domain": ".riverisland.com", "httpOnly": false, "name": "lang", "path": "/", "sameSite": "Lax", "secure": false, "value": "en"}, {"domain": "www.riverisland.com", "expiry": 1756940400, "httpOnly": false, "name": "intl_currency", "path": "/", "sameSite": "Lax", "secure": true, "value": "GBP"}, {"domain": ".riverisland.com", "expiry": 1760042188, "httpOnly": false, "name": "_ga", "path": "/", "sameSite": "Lax", "secure": false, "value": "GA1.2.1872015121.1725482187"}, {"domain": "www.riverisland.com", "httpOnly": false, "name": "intl_country", "path": "/", "sameSite": "Lax", "secure": true, "value": "GB"}]